[
  {
    "ENG_name": "Cinderskin",
    "name": "灰烬皮肤",
    "source": "ObojimaTallGrass",
    "page": 224,
    "type": "P",
    "resist": [
      "火焰"
    ],
    "rarity": "common",
    "property": [
      "Com"
    ],
    "entries": [
      "当你饮用这杯冒泡的黑色药水时，你的皮肤会覆盖上一层木炭。在1小时内，你将获得对火焰伤害的抗性。",
      {
        "type": "entries",
        "style": "text-center",
        "entries": [
          "{@font {@style 29|large}|SneakerProMedium}"
        ]
      }
    ],
    "miscTags": [
      "CNS"
    ],
    "fluff": {
      "images": [
        {
          "type": "image",
          "href": {
            "type": "external",
            "url": "https://raw.githubusercontent.com/TheGiddyLimit/homebrew-img/refs/heads/main/img/ObojimaTallGrass/Potions/Combat/cinderskin.webp"
          },
          "credit": "Scott Higginbotham",
          "width": 1423,
          "height": 1423
        }
      ]
    },
    "foundrySystem": {
      "uses": {
        "max": 1
      }
    }
  }
]