[
    {
        "ENG_name": "Sorcerous Origin",
        "name": "术法起源",
        "source": "PHB",
        "page": 99,
        "srd": true,
        "className": "术士",
        "classSource": "PHB",
        "level": 1,
        "entries": [
            "选择一个术法起源作为你天赋魔力的源泉。你将在第 1、第 6、第 14、第 18 级获得相应起源的职业特性。"
        ]
    },
    {
        "ENG_name": "Spellcasting",
        "name": "施法",
        "source": "PHB",
        "page": 99,
        "srd": true,
        "className": "术士",
        "classSource": "PHB",
        "level": 1,
        "entries": [
            "你体内先辈的血脉激发了你的奥法力量。魅力是你施展术士法术的关键属性。"
        ]
    },
    {
        "ENG_name": "Font of Magic",
        "name": "魔力泉涌",
        "source": "PHB",
        "page": 99,
        "srd": true,
        "className": "术士",
        "classSource": "PHB",
        "level": 2,
        "entries": [
            "第 2 级时，你解除了体内魔力之源的封印，体现为你的可用术法点。你可以使用术法点创造各种魔法效应。",
            {
                "type": "refClassFeature",
                "classFeature": "术法点|术士|PHB|2"
            },
            {
                "type": "refClassFeature",
                "classFeature": "灵活施法|术士|PHB|2"
            }
        ]
    },
    {
        "ENG_name": "Sorcery Points",
        "name": "术法点",
        "source": "PHB",
        "page": 99,
        "srd": true,
        "className": "术士",
        "classSource": "PHB",
        "level": 2,
        "header": 1,
        "entries": [
            "你拥有等于你术士等级的术法点（2 级时为 2 点）。每当你完成一次长休，你将重获所有消耗掉的术法点。"
        ]
    },
    {
        "ENG_name": "Flexible Casting",
        "name": "灵活施法",
        "source": "PHB",
        "page": 99,
        "srd": true,
        "className": "术士",
        "classSource": "PHB",
        "level": 2,
        "header": 1,
        "entries": [
            "你可以将术法点转换为法术位，或将法术位转换为术法点。",
            "{@b 创造法术位。} 你可以以你的附赠动作将剩余的术法点转换成一个法术位。创造一个法术位所需的术法点消耗见下表（你无法创造 6 环或更高环阶的法术位）：",
            {
                "type": "table",
                "caption": "创造法术位所需术法点",
                "colLabels": [
                    "法术位环阶",
                    "术法点消耗"
                ],
                "colStyles": [
                    "col-6 text-center",
                    "col-6 text-center"
                ],
                "rows": [
                    [
                        "1st",
                        "2"
                    ],
                    [
                        "2nd",
                        "3"
                    ],
                    [
                        "3rd",
                        "5"
                    ],
                    [
                        "4th",
                        "6"
                    ],
                    [
                        "5th",
                        "7"
                    ]
                ]
            },
            "{@b 献祭法术位。} 以一个附赠动作，你可以消耗一个法术位并获得等同于该法术位环阶数量的术法点。"
        ]
    },
    {
        "ENG_name": "Metamagic",
        "name": "超魔法",
        "source": "PHB",
        "page": 99,
        "srd": true,
        "className": "术士",
        "classSource": "PHB",
        "level": 3,
        "entries": [
            "第 3 级起，你获得了扭曲法术以适应你需求的能力。从可选的超魔法选项中选择两项，你在第 10 级和第 17 级时可以各再额外选择一项。",
            "除非每项超魔法的说明中另有规定，否则你每次施展法术时只能使用一个超魔法选项。"
        ]
    },
    {
        "ENG_name": "Ability Score Improvement",
        "name": "属性值提升",
        "source": "PHB",
        "page": 99,
        "srd": true,
        "className": "术士",
        "classSource": "PHB",
        "level": 4,
        "entries": [
            "当你达到第 4 级，以及之后的第 8、12、16、19 级时，你可以将你的一项属性值提升 2，或将两项属性值各提升 1。按常理，你不能通过此特性将属性值提升至 20 以上。如果你所使用的规则允许专长，你可以选择以本特性获得一个自选的专长。"
        ]
    },
    {
        "ENG_name": "Sorcerous Restoration",
        "name": "术法复苏",
        "source": "PHB",
        "page": 99,
        "srd": true,
        "className": "术士",
        "classSource": "PHB",
        "level": 20,
        "entries": [
            "第 20 级时，你每完成一次短休，可以恢复 4 点术法点。"
        ]
    }
]