[
  {
    "ENG_name": "Illusionist's Bracers",
    "name": "幻术师护臂",
    "source": "GGR",
    "page": 178,
    "rarity": "very rare",
    "reqAttune": "由施法者",
    "reqAttuneTags": [
      {
        "spellcasting": true
      }
    ],
    "wondrous": true,
    "entries": [
      "一位来自底密尔会堂的强大幻术师最初开发了这些护臂，使她能够同时创造多个次要幻象。然而护臂的功用远不止幻象方面。",
      "每当你在着装幻术师护臂时施放一个戏法，你可以在同一回合使用一个附赠动作再次施放该戏法。"
    ],
    "hasFluffImages": true,
    "valueReference": 40000,
    "fluff": {
      "images": [
        {
          "type": "image",
          "href": {
            "type": "internal",
            "path": "items/GGR/Illusionist's Bracers.webp"
          },
          "credit": "Svetlin Velinov",
          "width": 620,
          "height": 400
        }
      ]
    },
    "type": "W"
  }
]