[
  {
    "name": "天狗",
    "ENG_name": "Kenku",
    "source": "MPMM",
    "page": 24,
    "size": [
      "S",
      "M"
    ],
    "speed": 30,
    "skillProficiencies": [
      {
        "any": 2
      }
    ],
    "entries": [
      {
        "ENG_name": "Size",
        "name": "体型",
        "type": "entries",
        "entries": [
          "你的体型为中型或小型。当你选择该种族的时候进行决定。"
        ]
      },
      {
        "ENG_name": "Expert Duplication",
        "name": "复制专家",
        "type": "entries",
        "entries": [
          "当你抄写，或仿造你自己或其他人制作的工艺品时，你在用以制造一个一模一样复制品的属性检定中具有优势。"
        ]
      },
      {
        "ENG_name": "Kenku Recall",
        "name": "天狗回想",
        "type": "entries",
        "entries": [
          "多亏了你超自然的记忆力，你获得两项自选技能的熟练项。",
          "此外，当你使用任何你具有熟练的技能进行一次属性检定时，在你投掷{@dice d20}前，你可以让该检定具有优势。你可以使用这种方式给予自身优势的次数等于你的熟练加值，当你完成一次长休后，你重新获得所有消耗的次数。"
        ]
      },
      {
        "ENG_name": "Mimicry",
        "name": "拟声",
        "type": "entries",
        "entries": [
          "你可以确切地模仿你曾听到过的声音，包括嗓音。一个生物只有在进行一次成功的对抗DC为8+你熟练加值+你魅力调整值的感知（{@skill 洞悉}）检定后，才能听出你发出的声音是模仿的。"
        ]
      }
    ],
    "fluff": {
      "entries": [
        "天狗身披羽毛，形似渡鸦，被敏锐的观察力和超自然的准确记忆所祝福。没有一个天狗能记得他们的起源，但是他们经常开玩笑说，天狗有多少，天狗的起源故事就有多少。他们中的一些人将他们的起源描绘为一种诅咒，一种不会飞的鸟人，注定要模仿其他人的创作。其他的天狗则诵读着神秘而美丽的诗篇，关于他们的出现是一件喜事，因为他们可以到多元宇宙之中观察并且记录各种奇迹。",
        "无论他们真正的起源为何，天狗最常在堕影冥界和物质位面被发现，而且他们往往具有渡鸦的典型颜色。"
      ],
      "images": [
        {
          "type": "image",
          "href": {
            "type": "internal",
            "path": "races/MPMM/Kenku.webp"
          },
          "credit": "Scott Murphy",
          "width": 691,
          "height": 850
        }
      ]
    },
    "hasFluff": true,
    "hasFluffImages": true,
    "lineage": "VRGR",
    "soundClip": {
      "type": "internal",
      "path": "races/kenku.mp3"
    }
  }
]