[
  {
    "ENG_name": "Ruby Rod of Asmodeus",
    "name": "阿斯蒙蒂斯的红石法杖",
    "source": "CoA",
    "page": 274,
    "type": "RD|DMG",
    "rarity": "artifact",
    "reqAttune": true,
    "bonusWeapon": "+2",
    "recharge": "黄昏",
    "rechargeAmount": "{@dice 6d6}",
    "charges": 66,
    "entries": [
      "阿斯蒙蒂斯的红宝石法杖据说是由一块纯净邪恶的碎片制成，一颗浸泡在无辜者鲜血中的红宝石，来自龙神的唾液，以及777位天使的眼泪。这是一根具有晨星功能的魔法法杖，你对使用它的攻击和伤害骰有+2的加值。所有用它造成的伤害都转换为暗蚀伤害，当你击中一个善良阵营的生物时，那个生物会额外受到{@damage 2d12}暗蚀伤害。",
      "阿斯蒙蒂斯的红宝石法杖拥有66次充能，并在每个夜晚恢复{@dice 6d6}次充能。阿斯蒙蒂斯总是能够通过法杖感知，并知道任何与其共鸣的生物的确切位置。如果一个生物在没有阿斯蒙蒂斯许可的情况下使用法杖的特殊能力，他们每次使用会受到{@damage 2d12}点暗蚀伤害，如果是善良阵营则伤害翻倍。此伤害无视抗性和免疫，如果它杀死了使用者，阿斯蒙蒂斯将永久性地占有他们的灵魂。",
      {
        "ENG_name": "Random Properties",
        "name": "随机词条",
        "type": "entries",
        "entries": [
          "阿斯蒙蒂斯的红宝石法杖具有以下随机属性：",
          {
            "type": "list",
            "items": [
              "1项{@table 神器词条; 次要增益词条|DMG|次要增益}属性",
              "一个{@table 神器词条; 主要增益词条|DMG|主要增益}属性",
              "2项{@table 神器词条; 主要减益词条|DMG|主要减益}属性"
            ]
          },
          "阿斯蒙蒂斯对这件武器的有害属性免疫。"
        ]
      },
      {
        "ENG_name": "Bow to the King",
        "name": "向王致敬",
        "type": "entries",
        "entries": [
          "你可以使用一个动作来消耗33点充能以使用该法杖，迫使150英尺半径范围内的所有生物向你鞠躬。一个生物必须成功通过一个{@dc 21}的魅力豁免检定，否则将被强制跪下最多1小时。对{@condition 魅惑}状态免疫的生物在豁免检定上具有优势。每当一个跪下的生物受到伤害时，它可以重复豁免检定，成功则结束效果。如果跪下的生物被红宝石法杖触碰，效果也会提前结束。"
        ]
      },
      {
        "ENG_name": "Acid, Cold, and Lightning",
        "name": "强酸、冷冻和闪电",
        "type": "entries",
        "entries": [
          "每次使用需要消耗9个充能点，你可以采取动作来触发以下效果之一：",
          {
            "type": "list",
            "items": [
              "你投射出一条60英尺长、5英尺宽范围的酸液。该直线上的每个生物必须进行一次{@dc 18}敏捷豁免检定，检定失败时受到{@damage 12d8}点强酸伤害，检定成功则只受到一半伤害。",
              "作为一个动作，你可以施放 {@dc 19}（dc豁免 {@damage 12d8}）。在完成一次短休息或长休息后，你会恢复此能力。",
              "你向一条 90 英尺长、5 英尺宽的直线内释放闪电。该直线内的每个生物必须进行一次 {@dc 19} 敏捷豁免，豁免失败则受到 {@damage 12d10} 点闪电伤害，豁免成功则受到一半伤害。"
            ]
          }
        ]
      },
      {
        "ENG_name": "Reactions",
        "name": "反应",
        "type": "entries",
        "entries": [
          "作为对不利效果的反应，你可以施放{@spell 次等复原术}（消耗3个充能）或{@spell 高等复原术}（消耗12个充能）。",
          "此外，如果你是法术的唯一目标，你可以使用反应尝试使用魔杖吸收法术并取消其效果。你掷{@dice 1d20 + 2}，如果结果比法术等级+10高，法术就被吸收进魔杖。魔杖恢复等于它吸收的法术等级的充能次数。如果吸收的充能超过最大66次充能，它将过载，对你造成每充能{@damage 1d6}点暗蚀伤害，并消耗所有充能。"
        ]
      },
      {
        "ENG_name": "Destroying the Rod",
        "name": "摧毁法杖",
        "type": "entries",
        "entries": [
          "只要阿斯蒙蒂斯乌斯活着，阿斯蒙蒂斯乌斯的红宝石法杖就无法被摧毁，如果有人试图摧毁它，它将简单地返回到阿斯蒙蒂斯乌斯那里。如果他被击败，法杖可以通过将其带到它被创造的无底深渊，然后执行一个只有阿斯蒙蒂斯乌斯知道的仪式来摧毁。"
        ]
      }
    ],
    "attachedSpells": {
      "charges": {
        "3": [
          "次等复原术"
        ],
        "12": [
          "高等复原术"
        ]
      }
    },
    "hasFluffImages": true,
    "fluff": {
      "images": [
        {
          "type": "image",
          "href": {
            "type": "internal",
            "path": "items/CoA/Ruby Rod of Asmodeus and Scourge of Shadow.webp"
          },
          "title": "暗影之鞭（左）和阿斯蒙蒂斯的红宝石魔杖（右）",
          "credit": "Aaron Sims",
          "width": 943,
          "height": 1211
        }
      ]
    }
  }
]