[
  {
    "ENG_name": "Helm of the Gods",
    "name": "诸神之盔",
    "source": "MOT",
    "page": 196,
    "rarity": "rare",
    "reqAttune": true,
    "wondrous": true,
    "recharge": "拂晓",
    "rechargeAmount": "{@dice 1d3}",
    "charges": 3,
    "entries": [
      "戴上这个头盔的时候，你可以知道在你30尺范围内是否有天族或邪魔，以及该生物所在的位置，前提是该生物对你而言不处于{@quickref 掩护||3||全身掩护}。",
      "每当你戴着头盔完成一次长休时，你可以向诸神之盔表上列出的神明之一祈祷，并将所列的法术储存在头盔中，取代任何已经储存在那里的法术。法术的豁免DC为13。",
      "头盔有3发充能。你可以消耗1发充能来施展头盔中的法术。每日黎明时分，头盔恢复{@dice 1d3}发已消耗的充能。",
      {
        "type": "table",
        "colStyles": [
          "col-2 text-center",
          "col-10 text-center"
        ],
        "colLabels": [
          "神",
          "法术"
        ],
        "rows": [
          [
            "雅睿欧斯",
            "{@spell 防护善恶}"
          ],
          [
            "厄芳拉",
            "{@spell 庇护术}"
          ],
          [
            "厄睿柏斯",
            "{@spell 致伤术}"
          ],
          [
            "赫利欧德",
            "{@spell 光导箭}"
          ],
          [
            "伊洛安斯",
            "{@spell 英雄气概}"
          ],
          [
            "卡拉美特拉",
            "{@spell 神莓术}"
          ],
          [
            "刻拉诺斯",
            "{@spell 雷鸣斩}"
          ],
          [
            "克洛缇斯",
            "{@spell 纠缠术}"
          ],
          [
            "克罗芬斯",
            "{@spell 不谐低语}"
          ],
          [
            "墨癸司",
            "{@spell 炼狱叱喝}"
          ],
          [
            "倪勒娅",
            "{@spell 妖火}"
          ],
          [
            "芳瑞卡",
            "{@spell 次等复原术}"
          ],
          [
            "斐纳克",
            "{@spell 魅惑类人}"
          ],
          [
            "普罗烽斯",
            "{@spell 炽焰斩}"
          ],
          [
            "塔萨",
            "{@spell 鉴定术}"
          ]
        ]
      }
    ],
    "translator": "不全书",
    "valueReference": 4000,
    "type": "W"
  }
]