[
  {
    "ENG_name": "Plant Growth",
    "name": "植物滋长",
    "source": "XPHB",
    "page": 305,
    "srd52": true,
    "basicRules2024": true,
    "level": 3,
    "school": "T",
    "time": [
      {
        "number": 1,
        "unit": "动作",
        "note": "繁茂"
      },
      {
        "number": 8,
        "unit": "小时",
        "note": "丰产"
      }
    ],
    "range": {
      "type": "point",
      "distance": {
        "type": "feet",
        "amount": 150
      }
    },
    "components": {
      "v": true,
      "s": true
    },
    "duration": [
      {
        "type": "instant"
      }
    ],
    "entries": [
      "该法术将活力引导给特定区域中的植物。本法术的施法时间取决于你选择下述效应之一：繁茂或丰产。",
      {
        "ENG_name": "Overgrowth",
        "type": "entries",
        "name": "繁茂",
        "entries": [
          "你指定施法距离内一点，以该点为中心 100 尺半径的{@variantrule 球状 [效应区域]|XPHB|球状}范围内的普通植物将变的粗壮繁茂。一名穿过该区域的生物每移动 1 尺必须花费 4 尺移动力。你可以在该法术范围内空出一块或多块任意大小的区域，将其排除在法术效应影响之外。"
        ]
      },
      {
        "ENG_name": "Enrichment",
        "type": "entries",
        "name": "丰产",
        "entries": [
          "你指定施法距离内一点，距该点半里内的植物的产量将在 365 日内被强化。这些植物收获时将产出两倍于正常产量的作物。这些植物每年仅能从一道植物滋长中获益。"
        ]
      }
    ],
    "miscTags": [
      "DFT"
    ],
    "translator": "不全书",
    "classes": [
      "吟游诗人",
      "德鲁伊",
      "游侠"
    ],
    "display_school": "变化系"
  }
]