[
  {
    "ENG_name": "Harrowing Ballad",
    "name": "黯然销魂曲",
    "source": "CrookedMoon24",
    "page": 129,
    "level": 2,
    "school": "E",
    "time": [
      {
        "number": 1,
        "unit": "附赠动作"
      }
    ],
    "range": {
      "type": "point",
      "distance": {
        "type": "feet",
        "amount": 120
      }
    },
    "components": {
      "v": true,
      "s": true
    },
    "duration": [
      {
        "type": "timed",
        "duration": {
          "type": "minute",
          "amount": 1
        },
        "concentration": true
      }
    ],
    "entries": [
      "你对施法范围内一个你可见的生物施加一首侵蚀心智的歌谣。如果该生物的智力为4或更高，则其必须进行一次智力豁免检定，豁免失败则其在持续时间内陷入{@condition 魅惑|XPHB}状态。",
      "以这种方式被{@condition 魅惑|XPHB}期间，目标会被一首只有它能听见的、快速重复的民谣所折磨；它在其每个回合开始时受到{@damage 1d6}心灵伤害，并在感知（{@skill 察觉|XPHB}）检定以及用于维持{@status 专注|XPHB}的体质豁免中具有{@variantrule 劣势|XPHB}。目标在其每个回合结束时重复该豁免，豁免成功则终止自身该法术。"
    ],
    "entriesHigherLevel": [
      {
        "ENG_name": "Using a Higher-Level Spell Slot",
        "name": "升环施法",
        "type": "entries",
        "entries": [
          "伤害对每个高于2环的法术位环阶增加{@dice 1d6}。"
        ]
      }
    ],
    "classes": {
      "fromClassList": [
        {
          "ENG_name": "Bard",
          "name": "吟游诗人",
          "source": "XPHB"
        },
        {
          "ENG_name": "Sorcerer",
          "name": "术士",
          "source": "XPHB"
        },
        {
          "ENG_name": "Wizard",
          "name": "法师",
          "source": "XPHB"
        }
      ]
    },
    "damageInflict": [
      "心灵"
    ],
    "savingThrow": [
      "体质",
      "智力"
    ],
    "miscTags": [
      "SGT"
    ],
    "foundryImg": "https://raw.githubusercontent.com/TheGiddyLimit/homebrew-img/refs/heads/main/img/CrookedMoon24/Foundry/Spells/Harrowing-Ballad.webp"
  }
]