[
  {
    "ENG_name": "Sanguine Shield",
    "name": "血色盾牌",
    "source": "GrimHollowPG24",
    "page": 200,
    "level": 2,
    "school": "A",
    "subschools": [
      "血魔法"
    ],
    "time": [
      {
        "number": 1,
        "unit": "动作"
      }
    ],
    "range": {
      "type": "point",
      "distance": {
        "type": "self"
      }
    },
    "components": {
      "v": true,
      "s": true
    },
    "duration": [
      {
        "type": "timed",
        "duration": {
          "type": "minute",
          "amount": 1
        },
        "concentration": true
      }
    ],
    "entries": [
      "作为施放该法术的一部分，你必须消耗两个{@variantrule 生命值骰|XPHB}否则法术自动失败。你从周围受伤的生物身上汲取生命力，形成一个旋转的血色盾牌。你为30尺内每个{@variantrule 临时生命值|XPHB}未达最大值（包括你自己）的生物获得5{@variantrule 生命值|XPHB|生命值}，最多15{@variantrule 临时生命值|XPHB}。当你拥有该法术提供的{@variantrule 临时生命值|XPHB}时，你获得{@variantrule 掩护|XPHB|半身掩护}。当法术结束时，所有由此获得的{@variantrule 临时生命值|XPHB}都将消失。"
    ],
    "entriesHigherLevel": [
      {
        "ENG_name": "Using a Higher-Level Spell Slot",
        "name": "升环施法",
        "type": "entries",
        "entries": [
          "你获得的{@variantrule 临时生命值|XPHB}最大值每比2环高两个法术等级就增加5点。"
        ]
      }
    ],
    "classes": {
      "fromClassList": [
        {
          "ENG_name": "Sorcerer",
          "name": "术士",
          "source": "XPHB"
        },
        {
          "ENG_name": "Wizard",
          "name": "法师",
          "source": "XPHB"
        }
      ]
    },
    "miscTags": [
      "THP"
    ],
    "hasFluffImages": true,
    "foundryImg": "https://raw.githubusercontent.com/TheGiddyLimit/homebrew-img/main/img/GrimHollowPG24/Foundry/Spells/Sanguine%20Shield.webp"
  }
]