[
  {
    "ENG_name": "Summer Winds",
    "name": "夏日清风",
    "source": "CrookedMoon24",
    "page": 133,
    "level": 2,
    "school": "V",
    "time": [
      {
        "number": 1,
        "unit": "动作"
      }
    ],
    "range": {
      "type": "point",
      "distance": {
        "type": "self"
      }
    },
    "components": {
      "v": true,
      "s": true
    },
    "duration": [
      {
        "type": "instant"
      }
    ],
    "entries": [
      "你在15尺{@variantrule 锥状 [效应区域]|XPHB|锥状}区域内释放出一道光与风的冲击。{@variantrule 锥状 [效应区域]|XPHB|锥状}区域内你的盟友会恢复{@dice 2d6}{@variantrule 生命值|XPHB}。{@variantrule 锥状 [效应区域]|XPHB|锥状}区域内对你{@variantrule 敌对【态度】|XPHB|敌对}的亡灵必须进行一次体质豁免，豁免失败则受到{@damage 2d6}光耀伤害，豁免成功则受到半伤。"
    ],
    "entriesHigherLevel": [
      {
        "ENG_name": "Using a Higher-Level Spell Slot",
        "name": "升环施法",
        "type": "entries",
        "entries": [
          "使用的法术位每比二环高一环，伤害与治疗量就均增加{@dice 2d6}。"
        ]
      }
    ],
    "classes": {
      "fromClassList": [
        {
          "ENG_name": "Cleric",
          "name": "牧师",
          "source": "XPHB"
        },
        {
          "ENG_name": "Druid",
          "name": "德鲁伊",
          "source": "XPHB"
        },
        {
          "ENG_name": "Paladin",
          "name": "圣武士",
          "source": "XPHB"
        },
        {
          "ENG_name": "Ranger",
          "name": "游侠",
          "source": "XPHB"
        }
      ]
    },
    "damageInflict": [
      "光耀"
    ],
    "savingThrow": [
      "体质"
    ],
    "miscTags": [
      "HL"
    ],
    "foundryImg": "https://raw.githubusercontent.com/TheGiddyLimit/homebrew-img/refs/heads/main/img/CrookedMoon24/Foundry/Spells/Summer-Winds.webp"
  }
]