[
  {
    "ENG_name": "Phoenix Breastplate",
    "name": "凤凰胸甲",
    "source": "GriffonsSaddlebag2",
    "page": 136,
    "baseItem": "胸甲|phb",
    "type": "MA",
    "resist": [
      "火焰"
    ],
    "tier": "主要",
    "rarity": "very rare",
    "reqAttune": true,
    "weight": 20,
    "ac": 14,
    "bonusAc": "+1",
    "entries": [
      "这件金色胸甲的设计中融入了菲涅克斯的造型。在你穿着这件护甲期间，你的AC获得+1加值，并且你获得对火焰伤害的抗性。",
      "当你生命值降至0但未被直接杀死时，你可以选择改为降至1点生命值。当你这样做时，一股炽热的爆炸会包围你。30尺内的敌对生物必须进行一次DC 16的敏捷豁免检定，豁免失败时受到{@damage 3d10}火焰伤害，豁免成功时只受一半伤害。你和区域内的其他友好生物会恢复等同于该数值的生命值，而非受到火焰伤害。一旦护甲的这一属性被使用，在{@dice 1d6 + 1}天内无法再次使用。"
    ],
    "lootTables": [
      "魔法物品表 H1|GriffonsSaddlebag2"
    ],
    "fluff": {
      "images": [
        {
          "type": "image",
          "href": {
            "type": "external",
            "url": "https://raw.githubusercontent.com/TheGiddyLimit/homebrew-img/main/img/GriffonsSaddlebag2/Items/Phoenix-Breastplate.webp"
          },
          "width": 2400,
          "height": 2400
        }
      ]
    }
  }
]