[
  {
    "ENG_name": "Light",
    "name": "光亮术",
    "source": "PHB",
    "page": 255,
    "srd": true,
    "basicRules": true,
    "otherSources": [
      {
        "source": "RMR",
        "page": 55
      }
    ],
    "referenceSources": [
      "HotDQ",
      "OotA",
      "CoS",
      "LLK",
      "WDMM",
      "GoS",
      "SDW",
      "BGDIA",
      "IMR",
      "US",
      "RtG",
      "CRCotN",
      "KftGV",
      "PaBTSO"
    ],
    "reprintedAs": [
      "光亮术|XPHB"
    ],
    "level": 0,
    "school": "V",
    "time": [
      {
        "number": 1,
        "unit": "动作"
      }
    ],
    "range": {
      "type": "point",
      "distance": {
        "type": "touch"
      }
    },
    "components": {
      "v": true,
      "m": "一只萤火虫或萤光苔"
    },
    "duration": [
      {
        "type": "timed",
        "duration": {
          "type": "hour",
          "amount": 1
        }
      }
    ],
    "entries": [
      "你触碰一个尺寸在任意方向上都不超过 10 尺的物件。在法术终止前，物件将在其 20 尺半径范围内发出明亮光照，并在其外 20 尺范围发出微光光照。光的颜色由你决定，该物件被不透明的东西完全遮盖时，其光照被遮挡。如果你再次施展该法术，或者使用一个动作解散该法术，则该法术终止。",
      "如果你指定敌对生物所持握或着装的一个物件作为目标，则该生物必须进行一次敏捷豁免以尝试摆脱该法术的效应。"
    ],
    "savingThrow": [
      "dexterity"
    ],
    "miscTags": [
      "LGT",
      "OBJ"
    ],
    "translator": "不全书",
    "classes": [
      "吟游诗人",
      "牧师",
      "术士",
      "法师",
      "奇械师"
    ],
    "display_school": "塑能系",
    "display_savingThrow": [
      "敏捷"
    ]
  }
]