[
  {
    "name": "骑枪",
    "ENG_name": "Lance",
    "source": "XPHB",
    "page": 215,
    "edition": "one",
    "type": "M|XPHB",
    "rarity": "none",
    "weight": 6,
    "value": 1000,
    "weaponCategory": "martial",
    "property": [
      "H|XPHB",
      "R|XPHB",
      {
        "uid": "2H|XPHB",
        "note": "unless mounted"
      }
    ],
    "mastery": [
      "失衡|XPHB"
    ],
    "dmg1": "1d10",
    "dmgType": "P",
    "entries": [
      "当你没有骑乘时，长矛需要双手来挥舞。"
    ],
    "fluff": {
      "images": [
        {
          "type": "image",
          "href": {
            "type": "internal",
            "path": "items/XPHB/Lance.webp"
          },
          "credit": "Polar Engine",
          "width": 932,
          "height": 208
        }
      ]
    },
    "basicRules2024": true,
    "hasFluffImages": true,
    "lance": true,
    "srd52": true,
    "weapon": true
  }
]