[
  {
    "ENG_name": "Sticky Hand",
    "name": "混乱粘粘之手",
    "source": "ObojimaTallGrass",
    "page": 176,
    "rarity": "common",
    "wondrous": true,
    "entries": [
      "当你一手持握这件儿童玩具时，你可以施放{@spell 召物术|ObojimaTallGrass}法术。"
    ],
    "fluff": {
      "images": [
        {
          "type": "image",
          "href": {
            "type": "external",
            "url": "https://raw.githubusercontent.com/TheGiddyLimit/homebrew-img/refs/heads/main/img/ObojimaTallGrass/Items/sticky-hand.webp"
          },
          "credit": "Matt Owen",
          "width": 2661,
          "height": 2661
        }
      ]
    }
  }
]