[
  {
    "ENG_name": "Widemouth Bucket",
    "name": "宽嘴儿桶",
    "source": "GriffonsSaddlebag2",
    "page": 189,
    "tier": "次要",
    "rarity": "common",
    "wondrous": true,
    "weight": 3,
    "entries": [
      "这个黄铜吊桶呈鱼嘴开放形状，宽和高均为12寸，未装水时重3磅。这个吊桶最多可以装入10加仑液体，尽管它看起上只能装1加仑。无论桶内装入多少液体，吊桶的重量最多只增加1加仑液体的重量。"
    ],
    "lootTables": [
      "魔法物品表 A1|GriffonsSaddlebag2"
    ],
    "fluff": {
      "images": [
        {
          "type": "image",
          "href": {
            "type": "external",
            "url": "https://raw.githubusercontent.com/TheGiddyLimit/homebrew-img/main/img/GriffonsSaddlebag2/Items/Widemouth-Bucket.webp"
          },
          "width": 2400,
          "height": 2400
        }
      ]
    }
  }
]