[
  {
    "ENG_name": "Ride the Lightning",
    "name": "御电而行",
    "source": "GrimHollowPG24",
    "page": 198,
    "level": 4,
    "school": "C",
    "time": [
      {
        "number": 1,
        "unit": "动作"
      }
    ],
    "range": {
      "type": "point",
      "distance": {
        "type": "self"
      }
    },
    "components": {
      "v": true,
      "s": true,
      "m": "一段赤铜金属丝"
    },
    "duration": [
      {
        "type": "instant"
      }
    ],
    "entries": [
      "你将自身转化为一道闪电，在你当前空间和60尺内一个未占据空间之间创造一条5尺宽的{@variantrule 线状 [效应区域]|XPHB|线状}。处于{@variantrule 线状 [效应区域]|XPHB|线状}中的每个生物需进行一次敏捷豁免检定，豁免失败则受到{@damage 4d6}闪电伤害，豁免成功则只受到一半伤害。随后你在选定的空间重新出现。"
    ],
    "entriesHigherLevel": [
      {
        "ENG_name": "Using a Higher-Level Spell Slot",
        "name": "升环施法",
        "type": "entries",
        "entries": [
          "伤害每比4环高一个法术位环阶就增加{@dice 1d6}。此外，线状的最大长度每比4环高一个法术位环阶就增加10尺。"
        ]
      }
    ],
    "classes": {
      "fromClassList": [
        {
          "ENG_name": "Druid",
          "name": "德鲁伊",
          "source": "XPHB"
        },
        {
          "ENG_name": "Sorcerer",
          "name": "术士",
          "source": "XPHB"
        },
        {
          "ENG_name": "Wizard",
          "name": "法师",
          "source": "XPHB"
        }
      ]
    },
    "damageInflict": [
      "闪电"
    ],
    "savingThrow": [
      "敏捷"
    ],
    "hasFluffImages": true,
    "foundryImg": "https://raw.githubusercontent.com/TheGiddyLimit/homebrew-img/main/img/GrimHollowPG24/Foundry/Spells/Ride%20the%20Lightning.webp"
  }
]