[
  {
    "ENG_name": "Storm Stallion",
    "name": "风暴战驹",
    "source": "ObojimaTallGrass",
    "page": 190,
    "level": 4,
    "school": "V",
    "time": [
      {
        "number": 1,
        "unit": "动作"
      }
    ],
    "range": {
      "type": "point",
      "distance": {
        "type": "feet",
        "amount": 60
      }
    },
    "components": {
      "v": true,
      "s": true,
      "m": "风之花的茎"
    },
    "duration": [
      {
        "type": "instant"
      }
    ],
    "entries": [
      "选择一个你能看见的范围内5英尺立方的空间。一个中等大小的元素生物风暴战驹从旋转的造风术中出现在该空间，并向你选择的方向以直线冲锋最多60尺。如果战驹出现在一个被中型或更小的生物占据的空间，该生物必须成功通过一次敏捷豁免检定，否则会被战驹带着移动。生物可以选择在这次豁免检定中失败。",
      "风暴战驹路途上的每个生物（不包括它所携带的生物，如果有的话）必须进行一次敏捷豁免检定，豁免失败则受到{@damage 6d8}钝击伤害，豁免成功则只受到一半伤害。随后风暴战驹消失。"
    ],
    "entriesHigherLevel": [
      {
        "ENG_name": "At Higher Levels",
        "name": "升环施法效应",
        "type": "entries",
        "entries": [
          "当你使用5环或更高法术位施放该法术时，每比4环高一级，伤害就增加{@dice 1d8}。"
        ]
      }
    ],
    "classes": {
      "fromClassList": [
        {
          "ENG_name": "Druid",
          "name": "德鲁伊",
          "source": "PHB"
        },
        {
          "ENG_name": "Paladin",
          "name": "圣武士",
          "source": "PHB"
        },
        {
          "ENG_name": "Ranger",
          "name": "游侠",
          "source": "PHB"
        },
        {
          "ENG_name": "Sorcerer",
          "name": "术士",
          "source": "PHB"
        },
        {
          "ENG_name": "Warlock",
          "name": "魔契师",
          "source": "PHB"
        }
      ]
    },
    "damageInflict": [
      "钝击"
    ],
    "savingThrow": [
      "敏捷"
    ],
    "miscTags": [
      "SGT"
    ],
    "fluff": {
      "images": [
        {
          "type": "image",
          "href": {
            "type": "external",
            "url": "https://raw.githubusercontent.com/TheGiddyLimit/homebrew-img/refs/heads/main/img/ObojimaTallGrass/Spells/storm-stallion.webp"
          },
          "credit": "Alexander Cloos",
          "width": 2907,
          "height": 3480
        }
      ]
    },
    "foundryImg": "https://raw.githubusercontent.com/TheGiddyLimit/homebrew-img/refs/heads/main/img/ObojimaTallGrass/Custom/Spells/Storm%20Stallion.webp"
  }
]